{
    "Mygento": "❤️",
    "Имя": {
        "Разновидности имен": {
            "Распространенное": "Иван",
            "Редкое": "Розалия",
            "Короткое (min L)": "Ян",
            "Длинное (max L)": "Абдурахмангаджи",
            "Через дефис": "Анна-Мария",
            "Составное": "Мария Анна",
            "В составе буква Ё": "Чжи-хён",
            "Разные варианты написания имени": "Илья, Ильюша",
            "На английском": "Andrew",
            "Международные символы": "René",
            "Китайский": "泽东"
        },
        "Регистр букв": [
            "иван",
            "Иван",
            "ИВАН"
        ],
        "Пробелы": [
            "_Аня",
            "Аня_",
            "_Аня_"
        ],
        "Опечатка": "Сергейй",
        "Ограничение по количеству слов": [
            "Эрих Мария Ремарк"
        ],
        "Зарезервированные слова": [
            "Admin",
            "Ass"
        ],
        "Числа": [
            "Сергей123"
        ],
        "Эмодзи": [
            "🐕🐕🐕"
        ],
        "Спец.символы": [
            "Ivan!@#$%^&*()"
        ]
    }
}
